psycopg_toolbox/__init__.py
psycopg_toolbox/contextmanagers.py
psycopg_toolbox/exceptions.py
psycopg_toolbox/logging.py
psycopg_toolbox/py.typed
psycopg_toolbox/query_helpers.py
psycopg_toolbox/role_helpers.py
psycopg_toolbox/testfixtures.py
psycopg_toolbox-1.1.0.dist-info/METADATA
psycopg_toolbox-1.1.0.dist-info/WHEEL
psycopg_toolbox-1.1.0.dist-info/licenses/LICENSE
psycopg_toolbox-1.1.0.dist-info/RECORD
