Metadata-Version: 2.4
Name: psycopg-toolbox
Version: 1.1.0
Summary: A collection of useful utilities and context managers for working with psycopg3, including role switching, advisory locks, autocommit management, cloud environment detection, and custom exceptions. Designed to make common PostgreSQL operations more convenient and safer in async Python applications.
Project-URL: Homepage, https://github.com/jtbeach/psycopg-toolbox
Project-URL: Documentation, https://github.com/jtbeach/psycopg-toolbox#readme
Project-URL: Repository, https://github.com/jtbeach/psycopg-toolbox.git
Project-URL: Issues, https://github.com/yourusername/jtbeach-toolbox/issues
Author-email: Joel Beach <12853460+jtbeach@users.noreply.github.com>
License: MIT
License-File: LICENSE
Keywords: async,context-managers,database,postgresql,psycopg
Classifier: Development Status :: 4 - Beta
Classifier: Intended Audience :: Developers
Classifier: License :: OSI Approved :: MIT License
Classifier: Programming Language :: Python :: 3
Classifier: Programming Language :: Python :: 3.11
Classifier: Programming Language :: Python :: 3.12
Classifier: Topic :: Database
Classifier: Topic :: Database :: Front-Ends
Classifier: Topic :: Software Development :: Libraries :: Python Modules
Requires-Python: >=3.11
Requires-Dist: psycopg>=3.2.9
